slack_tunes/__init__.py
slack_tunes/updater.py
slack_tunes-0.4.1.data/scripts/slack-tunes
slack_tunes-0.4.1.dist-info/DESCRIPTION.rst
slack_tunes-0.4.1.dist-info/METADATA
slack_tunes-0.4.1.dist-info/RECORD
slack_tunes-0.4.1.dist-info/WHEEL
slack_tunes-0.4.1.dist-info/metadata.json
slack_tunes-0.4.1.dist-info/top_level.txt
slack_tunes-0.4.1.dist-info/zip-safe
