Metadata-Version: 2.0
Name: slack-tunes
Version: 0.4.1
Summary: send slack music notifications from spotify
Home-page: http://github.com/josegonzalez/python-slack-tunes
Author: Jose Diaz-Gonzalez
Author-email: slack-tunes@josediazgonzalez.com
License: The MIT License (MIT)
